lincal/__init__.py
lincal/__main__.py
lincal/static/css/fullscreen.css
lincal/static/css/styles.css
lincal/static/js/calendar.js
lincal/static/js/test-calendar.js
lincal/templates/index.html
lincal-0.3.1.dist-info/METADATA
lincal-0.3.1.dist-info/WHEEL
lincal-0.3.1.dist-info/entry_points.txt
lincal-0.3.1.dist-info/top_level.txt
lincal-0.3.1.dist-info/RECORD
