Metadata-Version: 2.4
Name: lincal
Version: 0.3.1
Summary: Linear Calendar Integration - Visualize Linear issues on a calendar interface
Author-email: Vishal Gandhi <igandhivishal@gmail.com>
License: MIT
Project-URL: Homepage, https://github.com/ivishalgandhi/linear-cal
Project-URL: Bug Tracker, https://github.com/ivishalgandhi/linear-cal/issues
Keywords: linear,calendar,task-management,flask
Classifier: Development Status :: 4 - Beta
Classifier: Environment :: Web Environment
Classifier: Framework :: Flask
Classifier: Intended Audience :: Developers
Classifier: License :: OSI Approved :: MIT License
Classifier: Programming Language :: Python :: 3
Classifier: Programming Language :: Python :: 3.8
Classifier: Programming Language :: Python :: 3.9
Classifier: Programming Language :: Python :: 3.10
Classifier: Topic :: Office/Business :: Scheduling
Requires-Python: >=3.8
Requires-Dist: flask==2.3.3
Requires-Dist: requests==2.31.0
Requires-Dist: python-dotenv==1.0.0
Requires-Dist: flask-cors==4.0.0
